snakemake_storage_plugin_orcestra/__init__.py
snakemake_storage_plugin_orcestra-0.2.0.dist-info/METADATA
snakemake_storage_plugin_orcestra-0.2.0.dist-info/WHEEL
snakemake_storage_plugin_orcestra-0.2.0.dist-info/RECORD
