Metadata-Version: 2.4
Name: snakemake-storage-plugin-orcestra
Version: 0.2.0
Project-URL: repository, https://github.com/bhklab/snakemake-storage-plugin-orcestra
Project-URL: documentation, https://snakemake.github.io/snakemake-plugin-catalog/plugins/storage/orcestra.html
Author-email: Jermiah Joseph <jermiahjoseph98@gmail.com>
License-Expression: MIT
Keywords: google cloud storage,plugin,snakemake,storage
Requires-Python: >=3.11
Requires-Dist: orcestra-downloader
Requires-Dist: snakemake-interface-common<2.0.0,>=1.17.4
Requires-Dist: snakemake-interface-storage-plugins<4.0.0,>=3.3.0
